yaml4rst/cli.py
yaml4rst/reformatter.py
yaml4rst/__init__.py
yaml4rst/_meta.py
yaml4rst/defaults.py
yaml4rst/helpers.py
yaml4rst/templates/debops/ansible/defaults_header.j2
yaml4rst-0.1.6.dist-info/RECORD
yaml4rst-0.1.6.dist-info/top_level.txt
yaml4rst-0.1.6.dist-info/entry_points.txt
yaml4rst-0.1.6.dist-info/metadata.json
yaml4rst-0.1.6.dist-info/DESCRIPTION.rst
yaml4rst-0.1.6.dist-info/WHEEL
yaml4rst-0.1.6.dist-info/METADATA
