Metadata-Version: 2.0
Name: yaml4rst
Version: 0.1.6
Summary: Linting/reformatting tool for YAML files documented with inline RST
Home-page: https://github.com/ypid/yaml4rst
Author: Robin Schneider
Author-email: ypid@riseup.net
License: AGPL-3.0
Keywords: YML YAML RST reStructuresText Ansible DebOps linting docs documentation
Platform: UNKNOWN
Classifier: Development Status :: 4 - Beta
Classifier: Environment :: Console
Classifier: Intended Audience :: Developers
Classifier: Intended Audience :: System Administrators
Classifier: License :: DFSG approved
Classifier: License :: OSI Approved :: GNU Affero General Public License v3
Classifier: Natural Language :: English
Classifier: Operating System :: OS Independent
Classifier: Programming Language :: Python :: 3
Classifier: Programming Language :: Python :: 3.3
Classifier: Programming Language :: Python :: 3.4
Classifier: Programming Language :: Python :: 3.5
Classifier: Programming Language :: Python :: 3.6
Classifier: Topic :: Software Development :: Documentation
Classifier: Topic :: Software Development :: Quality Assurance
Classifier: Topic :: Text Processing
Requires-Dist: PyYAML
Requires-Dist: Jinja2
Provides-Extra: test
Requires-Dist: nose; extra == 'test'
Requires-Dist: nose2; extra == 'test'
Requires-Dist: testfixtures; extra == 'test'
Requires-Dist: tox; extra == 'test'
Requires-Dist: flake8; extra == 'test'
Requires-Dist: pylint; extra == 'test'
Requires-Dist: coverage; extra == 'test'
Requires-Dist: yamllint; extra == 'test'
